itests/__init__.py
itests/pliptv/__init__.py
itests/pliptv/m3u_test.py
itests/pliptv/pl_filters/__init__.py
itests/pliptv/pl_filters/filters_test.py
pliptv/__init__.py
pliptv/azure_service.py
pliptv/cli_questions.py
pliptv/config_loader.py
pliptv/epg_service.py
pliptv/m3u_utils.py
pliptv/main.py
pliptv/picons_service.py
pliptv/models/__init__.py
pliptv/models/epg.py
pliptv/models/streams.py
pliptv/pl_filters/__init__.py
pliptv/pl_filters/accepted_filter.py
pliptv/pl_filters/clean_name_filter.py
pliptv/pl_filters/display_name_filter.py
pliptv/pl_filters/epg_filter.py
pliptv/pl_filters/filter_abc.py
pliptv/pl_filters/filters_loader.py
pliptv/pl_filters/grouping_filter.py
pliptv/pl_filters/picon_filter.py
pliptv/pl_filters/quality_filter.py
pliptv/pl_filters/remove_headers_filter.py
pliptv/pl_filters/shift_filter.py
pliptv/pl_filters/vod_filter.py
pliptv/utils/__init__.py
pliptv/utils/tools.py
pliptv/utils/log/__init__.py
pliptv/utils/log/decorators.py
pliptv/utils/log/logging_meta.py
xplcli-0.1.7.dist-info/LICENSE
xplcli-0.1.7.dist-info/METADATA
xplcli-0.1.7.dist-info/WHEEL
xplcli-0.1.7.dist-info/entry_points.txt
xplcli-0.1.7.dist-info/top_level.txt
xplcli-0.1.7.dist-info/RECORD
