Metadata-Version: 2.1
Name: xplcli
Version: 0.1.7
Summary: Simple extensible m3u playlist manager cli
Home-page: https://github.com/Fazzani/pliptvcli
Author: Heni FAZZANI
Author-email: heni.fazzani@gmail.com
License: MIT
Classifier: Programming Language :: Python :: 3
Classifier: License :: OSI Approved :: MIT License
Classifier: Operating System :: OS Independent
License-File: LICENSE
Requires-Dist: xcodestream==0.0.8
Requires-Dist: azure-storage-blob~=12.24.0
Requires-Dist: requests~=2.32.0
Requires-Dist: pyshorteners==1.0.1
Requires-Dist: Munch~=4.0.0
Requires-Dist: pyyaml~=6.0.2
Requires-Dist: memoization==0.4.0
Requires-Dist: Click~=8.1.7
Requires-Dist: docopt==0.6.2
Requires-Dist: PyFiglet~=1.0.2
Requires-Dist: Clint==0.5.1
Requires-Dist: PyInquirer~=1.0.3
Requires-Dist: termcolor~=2.5.0
Requires-Dist: coloredlogs==15.0
Requires-Dist: validators~=0.34.0
Requires-Dist: tqdm~=4.67.0
Requires-Dist: jsonpickle~=4.0.0
